README.md
setup.py
django_slack_utils.egg-info/PKG-INFO
django_slack_utils.egg-info/SOURCES.txt
django_slack_utils.egg-info/dependency_links.txt
django_slack_utils.egg-info/not-zip-safe
django_slack_utils.egg-info/top_level.txt
slack_utils/__init__.py
slack_utils/apps.py
slack_utils/commands.py
slack_utils/decorators.py
slack_utils/forms.py
slack_utils/models.py
slack_utils/signals.py
slack_utils/urls.py
slack_utils/verification.py
slack_utils/views.py