Metadata-Version: 1.2
Name: django-slack-utils
Version: 0.2.0
Summary: A Django app for handling Slack webhooks
Home-page: https://github.com/startmatter/django-slack-utils
Author: Dmitry Demidenko
Author-email: dmitry.demidenko@startmatter.com
Maintainer: Dmitry Demidenko
Maintainer-email: dmitry.demidenko@startmatter.com
License: BSD
Keywords: slack,django
Platform: UNKNOWN
Classifier: Development Status :: 5 - Production/Stable
Classifier: Environment :: Web Environment
Classifier: Framework :: Django
Classifier: Intended Audience :: Developers
Classifier: Framework :: Django
Classifier: Framework :: Django :: 1.11
Classifier: Framework :: Django :: 2.0
Classifier: License :: OSI Approved :: BSD License
Classifier: Operating System :: OS Independent
Classifier: Programming Language :: Python
Classifier: Programming Language :: Python :: 3
Classifier: Programming Language :: Python :: 3.4
Classifier: Programming Language :: Python :: 3.5
Classifier: Programming Language :: Python :: 3.6
Classifier: Programming Language :: Python :: 3.7
